pokepoke/__init__.py
pokepoke/pokemon.py
PokePoke-0.0.1.dist-info/LICENSE
PokePoke-0.0.1.dist-info/METADATA
PokePoke-0.0.1.dist-info/WHEEL
PokePoke-0.0.1.dist-info/top_level.txt
PokePoke-0.0.1.dist-info/RECORD
