Metadata-Version: 2.1
Name: PokePoke
Version: 0.0.1
Summary: Simple library to get information about pokemon
Home-page: https://github.com/SeladaKeju/Pokemon
Author: SeladaKeju
Author-email: <rizqiadit2430@gmail.com>
Keywords: Poke,Pokemon
Classifier: Development Status :: 1 - Planning
License-File: LICENSE
